samitizer/__init__.py
samitizer/const.py
samitizer/sami.py
samitizer/subtitle.py
tests/__init__.py
tests/test.py
samitizer-0.2.3.dist-info/LICENSE
samitizer-0.2.3.dist-info/METADATA
samitizer-0.2.3.dist-info/WHEEL
samitizer-0.2.3.dist-info/top_level.txt
samitizer-0.2.3.dist-info/RECORD
